cdpackage/__init__.py
webscrape_cd-1.0.dist-info/LICENSE
webscrape_cd-1.0.dist-info/METADATA
webscrape_cd-1.0.dist-info/WHEEL
webscrape_cd-1.0.dist-info/top_level.txt
webscrape_cd-1.0.dist-info/RECORD
